.travis.yml
AUTHORS
ChangeLog
LICENSE.txt
README.md
README.rst
requirements.txt
setup.cfg
setup.py
emojicons/__init__.py
emojicons/emoji.py
emojicons.egg-info/PKG-INFO
emojicons.egg-info/SOURCES.txt
emojicons.egg-info/dependency_links.txt
emojicons.egg-info/entry_points.txt
emojicons.egg-info/not-zip-safe
emojicons.egg-info/pbr.json
emojicons.egg-info/requires.txt
emojicons.egg-info/top_level.txt