Metadata-Version: 1.1
Name: emojicons
Version: 2.0.1
Summary: A very small python script that exposes a CLI and consumes http://emojicons.com/
Home-page: UNKNOWN
Author: Mario Santos
Author-email: mario.rf.santos@gmail.com
License: UNKNOWN
Platform: UNKNOWN
Classifier: License :: OSI Approved :: MIT License
Classifier: Programming Language :: Python
Classifier: Programming Language :: Python :: 2
Classifier: Programming Language :: Python :: 2.7
Classifier: Programming Language :: Python :: 3
Classifier: Programming Language :: Python :: 3.7
